algocli/__init__.py
algocli/__main__.py
algocli/algocli.py
algocli/errors.py
algocli/replacer.py
algocli/util.py
algocli-0.2.dist-info/LICENSE
algocli-0.2.dist-info/METADATA
algocli-0.2.dist-info/WHEEL
algocli-0.2.dist-info/entry_points.txt
algocli-0.2.dist-info/top_level.txt
algocli-0.2.dist-info/RECORD
