Metadata-Version: 2.1
Name: algocli
Version: 0.2
Summary: print common algorithms to the command line
Home-page: https://github.com/emanuel2718/algocli
Author: Emanuel Ramirez Alsina
Author-email: eramirez2718@gmail.com
Maintainer: Emanuel Ramirez Alsina
Maintainer-email: eramirez2718@gmail.com
License: MIT
Keywords: algocli algorithms console command line
Platform: UNKNOWN
Classifier: Development Status :: 3 - Alpha
Classifier: Environment :: Console
Classifier: Intended Audience :: Developers
Classifier: Programming Language :: Python :: 3
Classifier: Programming Language :: Python :: 3.6
Classifier: Programming Language :: Python :: 3.7
Classifier: Programming Language :: Python :: 3.8
Classifier: Programming Language :: Python :: 3.9
Classifier: Topic :: Documentation
Requires-Python: >=3.6
Requires-Dist: Pygments
Requires-Dist: bs4
Requires-Dist: requests
Requires-Dist: setuptools
